MANIFEST.in
README.md
setup.py
bin/compose-deploy
compose_deploy/__init__.py
compose_deploy/_main.py
compose_deploy/remote.py
compose_deploy.egg-info/PKG-INFO
compose_deploy.egg-info/SOURCES.txt
compose_deploy.egg-info/dependency_links.txt
compose_deploy.egg-info/requires.txt
compose_deploy.egg-info/top_level.txt