Metadata-Version: 1.1
Name: compose-deploy
Version: 0.1.5
Summary: A wrapper around docker-compose to aid in deploying to a remote server.
Home-page: https://github.com/KitB/compose-deploy
Author: Kit Barnes
Author-email: k.barnes@mhnltd.co.uk
License: MIT
Platform: UNKNOWN
Classifier: Development Status :: 2 - Pre-Alpha
Classifier: License :: OSI Approved :: MIT License
Classifier: Programming Language :: Python
Classifier: Programming Language :: Python :: 2.6
Classifier: Programming Language :: Python :: 2.7
